mine/__init__.py
mine/keys/__init__.py
mine/keys/base.py
mine/keys/helper.py
mine/keys/keys.py
mine/keys/schemas.py
mine/keys/serializer.py
mine/keys/storage.py
mine_assistant-1.0.2.dist-info/LICENSE
mine_assistant-1.0.2.dist-info/METADATA
mine_assistant-1.0.2.dist-info/WHEEL
mine_assistant-1.0.2.dist-info/top_level.txt
mine_assistant-1.0.2.dist-info/RECORD
