Metadata-Version: 2.1
Name: mine-assistant
Version: 1.0.2
Summary: Personal custom supporting package
Home-page: https://github.com/lovesh-kumrawat/mine
Download-URL: https://pypi.org/project/mine-assistant/
Author: Lovesh Kumrawat
Author-email: kumrawat.lovesh@gmail.com
Maintainer: Lovesh Kumrawat
Maintainer-email: kumrawat.lovesh@gmail.com
License: MIT License
Keywords: mine,api-keys,key-store,env-setup,llm-keys,secure-keys
Platform: ALL
Classifier: Development Status :: 3 - Alpha
Classifier: Intended Audience :: Developers
Classifier: License :: OSI Approved :: MIT License
Classifier: Operating System :: OS Independent
Classifier: Programming Language :: Python :: 3.10
Classifier: Topic :: Software Development
Requires-Python: >=3.10
License-File: LICENSE
